nextgen_kernels_api/__init__.py
nextgen_kernels_api/gateway/__init__.py
nextgen_kernels_api/gateway/managers.py
nextgen_kernels_api/services/__init__.py
nextgen_kernels_api/services/kernels/__init__.py
nextgen_kernels_api/services/kernels/client.py
nextgen_kernels_api/services/kernels/kernelmanager.py
nextgen_kernels_api/services/kernels/message_utils.py
nextgen_kernels_api/services/kernels/states.py
nextgen_kernels_api/services/kernels/connection/__init__.py
nextgen_kernels_api/services/kernels/connection/kernel_client_connection.py
nextgen_kernels_api-0.11.0.dist-info/METADATA
nextgen_kernels_api-0.11.0.dist-info/WHEEL
nextgen_kernels_api-0.11.0.dist-info/licenses/LICENSE.txt
nextgen_kernels_api-0.11.0.dist-info/RECORD
