Metadata-Version: 2.4
Name: nextgen-kernels-api
Version: 0.11.0
Summary: Next-generation Jupyter kernel management with decoupled client connections
Author-email: Zach Sailer <zsailer@apple.com>
License: BSD-3-Clause
License-File: LICENSE.txt
Classifier: Development Status :: 3 - Alpha
Classifier: Framework :: Jupyter
Classifier: Intended Audience :: Developers
Classifier: License :: OSI Approved :: BSD License
Classifier: Programming Language :: Python :: 3
Classifier: Programming Language :: Python :: 3.8
Classifier: Programming Language :: Python :: 3.9
Classifier: Programming Language :: Python :: 3.10
Classifier: Programming Language :: Python :: 3.11
Classifier: Programming Language :: Python :: 3.12
Requires-Python: >=3.9
Requires-Dist: jupyter-client>=8.0.0
Requires-Dist: jupyter-server>=2.0.0
Requires-Dist: traitlets>=5.0.0
Provides-Extra: dev
Requires-Dist: black>=23.0.0; extra == 'dev'
Requires-Dist: pytest-asyncio>=0.21.0; extra == 'dev'
Requires-Dist: pytest-jupyter[server]>=0.10.0; extra == 'dev'
Requires-Dist: pytest-timeout>=2.0.0; extra == 'dev'
Requires-Dist: pytest>=7.0.0; extra == 'dev'
Requires-Dist: ruff>=0.1.0; extra == 'dev'
